cryx4ck/__init__.py
cryx4ck/crypto.py
cryx4ck/hash.py
cryx4ck-1.2.dist-info/License
cryx4ck-1.2.dist-info/METADATA
cryx4ck-1.2.dist-info/WHEEL
cryx4ck-1.2.dist-info/top_level.txt
cryx4ck-1.2.dist-info/RECORD
