Metadata-Version: 2.1
Name: cryx4ck
Version: 1.2
Summary: This Python project offers a versatile and user-friendly text encryption and decryption tool inspired by Base64 encoding. Whether you're securing sensitive information or looking to obfuscate data, this library provides a robust and straightforward solution.
Home-page: https://github.com/mrc72tr54/cryx4ck/
Author: mrc72tr54
Author-email: rakib4ggp@gmail.com
License: License
Classifier: Development Status :: 5 - Production/Stable
Classifier: Intended Audience :: Developers
Classifier: Natural Language :: English
Classifier: License :: OSI Approved :: Apache Software License
Classifier: Programming Language :: Python
Classifier: Programming Language :: Python :: 2
Classifier: Programming Language :: Python :: 2.7
Classifier: Programming Language :: Python :: 3
Classifier: Programming Language :: Python :: 3.5
Classifier: Programming Language :: Python :: 3.6
Classifier: Programming Language :: Python :: 3.7
Classifier: Programming Language :: Python :: 3.8
Classifier: Programming Language :: Python :: 3.9
Classifier: Programming Language :: Python :: Implementation :: CPython
Classifier: Programming Language :: Python :: Implementation :: PyPy
License-File: License
Requires-Dist: bitarray
